delayed_import/__init__.py
delayed_import/core.py
delayed_import/dict_tree.py
delayed_import/lazy_module.py
delayed_import/module_registry.py
delayed_import/py.typed
delayed_import-0.1.0.dist-info/METADATA
delayed_import-0.1.0.dist-info/WHEEL
delayed_import-0.1.0.dist-info/licenses/LICENSE.md
delayed_import-0.1.0.dist-info/RECORD
