Metadata-Version: 2.4
Name: delayed-import
Version: 0.1.0
Summary: A Python library that lets you delay module imports to when the import is used.
Author-email: Nardi Lam <mail@nardilam.nl>
License-Expression: MIT
License-File: LICENSE.md
Classifier: Development Status :: 3 - Alpha
Classifier: Intended Audience :: Developers
Classifier: License :: OSI Approved :: MIT License
Classifier: Programming Language :: Python :: 3
Classifier: Programming Language :: Python :: 3.11
Classifier: Topic :: Software Development :: Libraries :: Python Modules
Requires-Python: >=3.11
Requires-Dist: lazy-object-proxy>=1.11.0
